aiohttp_debugtoolbar/__init__.py
aiohttp_debugtoolbar/main.py
aiohttp_debugtoolbar/middlewares.py
aiohttp_debugtoolbar/py.typed
aiohttp_debugtoolbar/toolbar.py
aiohttp_debugtoolbar/utils.py
aiohttp_debugtoolbar/views.py
aiohttp_debugtoolbar/panels/__init__.py
aiohttp_debugtoolbar/panels/base.py
aiohttp_debugtoolbar/panels/headers.py
aiohttp_debugtoolbar/panels/logger.py
aiohttp_debugtoolbar/panels/middlewares.py
aiohttp_debugtoolbar/panels/performance.py
aiohttp_debugtoolbar/panels/request_vars.py
aiohttp_debugtoolbar/panels/routes.py
aiohttp_debugtoolbar/panels/settings.py
aiohttp_debugtoolbar/panels/traceback.py
aiohttp_debugtoolbar/panels/versions.py
aiohttp_debugtoolbar/panels/templates/headers.jinja2
aiohttp_debugtoolbar/panels/templates/logger.jinja2
aiohttp_debugtoolbar/panels/templates/middlewares.jinja2
aiohttp_debugtoolbar/panels/templates/performance.jinja2
aiohttp_debugtoolbar/panels/templates/request_vars.jinja2
aiohttp_debugtoolbar/panels/templates/routes.jinja2
aiohttp_debugtoolbar/panels/templates/settings.jinja2
aiohttp_debugtoolbar/panels/templates/sqlalchemy_explain.jinja2
aiohttp_debugtoolbar/panels/templates/sqlalchemy_select.jinja2
aiohttp_debugtoolbar/panels/templates/traceback.jinja2
aiohttp_debugtoolbar/panels/templates/versions.jinja2
aiohttp_debugtoolbar/static/css/bootstrap.min.css
aiohttp_debugtoolbar/static/css/dashboard.css
aiohttp_debugtoolbar/static/css/debugger.css
aiohttp_debugtoolbar/static/css/highlightjs_default.min.css
aiohttp_debugtoolbar/static/css/prism.css
aiohttp_debugtoolbar/static/css/toolbar.css
aiohttp_debugtoolbar/static/css/toolbar_button.css
aiohttp_debugtoolbar/static/font/FONT_LICENSE
aiohttp_debugtoolbar/static/font/ubuntu.ttf
aiohttp_debugtoolbar/static/fonts/glyphicons-halflings-regular.eot
aiohttp_debugtoolbar/static/fonts/glyphicons-halflings-regular.svg
aiohttp_debugtoolbar/static/fonts/glyphicons-halflings-regular.ttf
aiohttp_debugtoolbar/static/fonts/glyphicons-halflings-regular.woff
aiohttp_debugtoolbar-0.6.1.dist-info/LICENSE
aiohttp_debugtoolbar-0.6.1.dist-info/METADATA
aiohttp_debugtoolbar-0.6.1.dist-info/WHEEL
aiohttp_debugtoolbar-0.6.1.dist-info/top_level.txt
aiohttp_debugtoolbar-0.6.1.dist-info/RECORD
