Metadata-Version: 2.1
Name: aiohttp-debugtoolbar
Version: 0.6.1
Summary: debugtoolbar for aiohttp
Home-page: https://github.com/aio-libs/aiohttp_debugtoolbar
Author: Nikolay Novik
Author-email: nickolainovik@gmail.com
License: Apache 2
Classifier: License :: OSI Approved :: Apache Software License
Classifier: Intended Audience :: Developers
Classifier: Programming Language :: Python
Classifier: Programming Language :: Python :: 3
Classifier: Programming Language :: Python :: 3.8
Classifier: Programming Language :: Python :: 3.9
Classifier: Programming Language :: Python :: 3.10
Classifier: Programming Language :: Python :: 3.11
Classifier: Topic :: Internet :: WWW/HTTP
Classifier: Framework :: AsyncIO
License-File: LICENSE
Requires-Dist: aiohttp >=3.9
Requires-Dist: aiohttp-jinja2
